Metadata-Version: 2.1
Name: ostrat
Version: 1.0.5
Summary: Open-Source Telegram Remote Administration Tool - Remote PC access via Telegram Bot.
Home-page: https://sourceforge.net/projects/ostrat/
Author: lexek
Author-email: minelanpro@gmail.ru
License: OSI Approved :: GNU General Public License v3 (GPLv3)
Download-URL: https://sourceforge.net/projects/ostrat/files/ostRAT/
Platform: UNKNOWN
Classifier: License :: OSI Approved :: GNU General Public License v3 (GPLv3)
Classifier: Operating System :: Microsoft :: Windows
Classifier: Development Status :: 4 - Beta
Classifier: Environment :: Console
Classifier: Topic :: System :: Systems Administration
Classifier: Intended Audience :: System Administrators
Classifier: Intended Audience :: Information Technology
Classifier: Programming Language :: Python
Classifier: Programming Language :: Python :: 3.10
License-File: LICENSE
